mkmd/__init__.py
mkmd/utils.py
mkmd-0.0.1.dist-info/METADATA
mkmd-0.0.1.dist-info/WHEEL
mkmd-0.0.1.dist-info/top_level.txt
mkmd-0.0.1.dist-info/RECORD
