Metadata-Version: 2.1
Name: mkmd
Version: 0.0.1
Summary: Make Markdown Documents
License: MIT
Project-URL: Repository, https://github.com/phoenixr-codes/mkmd/
Project-URL: Documentation, https://phoenixr-codes.github.io/mkmd/
Keywords: Documentation,Generator,Markdown,Markup
Classifier: Development Status :: 5 - Production/Stable
Classifier: Intended Audience :: Developers
Classifier: License :: OSI Approved :: MIT License
Classifier: Natural Language :: English
Classifier: Programming Language :: Python :: 3
Classifier: Programming Language :: Python :: 3 :: Only
Classifier: Programming Language :: Python :: Implementation :: CPython
Classifier: Topic :: Documentation
Classifier: Topic :: Software Development :: Documentation
Classifier: Topic :: Text Processing :: Markup
Classifier: Topic :: Text Processing :: Markup :: Markdown
Classifier: Topic :: Utilities
Classifier: Typing :: Typed
Requires-Python: >=3.7
Provides-Extra: docs
Requires-Dist: Sphinx ; extra == 'docs'
Requires-Dist: sphinx-book-theme ; extra == 'docs'
Requires-Dist: sphinx-copybutton ; extra == 'docs'
